setup.py
piped.contrib.validation.egg-info/PKG-INFO
piped.contrib.validation.egg-info/SOURCES.txt
piped.contrib.validation.egg-info/dependency_links.txt
piped.contrib.validation.egg-info/requires.txt
piped.contrib.validation.egg-info/top_level.txt
piped/plugins/validation_processors.py
piped_validation/__init__.py
piped_validation/processors.py
piped_validation/test/__init__.py
piped_validation/test/test_validation_processors.py